scoary/GUI.py
scoary/__init__.py
scoary/citation.py
scoary/classes.py
scoary/methods.py
scoary/nwkhandler.py
scoary/vcf2scoary.py
scoary/exampledata/Example.vcf
scoary/exampledata/ExampleTree.nwk
scoary/exampledata/ExampleVCFTrait.csv
scoary/exampledata/Gene_presence_absence.csv
scoary/exampledata/Restrict_to.csv
scoary/exampledata/Tetracycline_resistance.csv
scoary-1.6.16.dist-info/DESCRIPTION.rst
scoary-1.6.16.dist-info/METADATA
scoary-1.6.16.dist-info/RECORD
scoary-1.6.16.dist-info/WHEEL
scoary-1.6.16.dist-info/entry_points.txt
scoary-1.6.16.dist-info/metadata.json
scoary-1.6.16.dist-info/top_level.txt
