Metadata-Version: 2.0
Name: scoary
Version: 1.6.16
Summary: Microbial pan-GWAS using the output from Roary
Home-page: https://github.com/AdmiralenOla/Scoary
Author: Ola Brynildsrud
Author-email: ola.brynildsrud@fhi.no
License: GPLv3
Download-URL: https://github.com/AdmiralenOla/Scoary/tarball/v1.6.16
Keywords: microbial,genomics,GWAS,Roary
Platform: UNKNOWN
Classifier: Development Status :: 4 - Beta
Classifier: License :: OSI Approved :: GNU General Public License v3 (GPLv3)
Classifier: Programming Language :: Python :: 2.7
Classifier: Topic :: Scientific/Engineering :: Bio-Informatics
Classifier: Topic :: Scientific/Engineering :: Medical Science Apps.
Classifier: Intended Audience :: Science/Research
Requires-Dist: argparse
Requires-Dist: scipy (>=0.16)
